cases/__init__.py
cases/breakwaters/__init__.py
cases/breakwaters/breakwaters_utils.py
cases/breakwaters/arctic_config/__init__.py
cases/breakwaters/arctic_config/arctic_config.py
cases/breakwaters/configuration_de/__init__.py
cases/breakwaters/configuration_de/bw_domain.py
cases/breakwaters/configuration_de/bw_estimator.py
cases/breakwaters/configuration_de/bw_optimizer.py
cases/breakwaters/configuration_de/bw_sampler.py
cases/breakwaters/configuration_spea2/__init__.py
cases/breakwaters/configuration_spea2/bw_estimator.py
cases/breakwaters/configuration_spea2/bw_optimizer.py
cases/breakwaters/configuration_spea2/bw_sampler.py
cases/breakwaters/configuration_surrogate/__init__.py
cases/breakwaters/configuration_surrogate/bw_estimator.py
cases/heat/__init__.py
cases/heat/main.py
cases/heat/configuration_dl/__init__.py
cases/heat/configuration_dl/heat_estimator.py
cases/heat/configuration_dl/heat_sampler.py
cases/microfluidic/__init__.py
cases/microfluidic/config_standard.py
cases/microfluidic/configuration_dl/__init__.py
cases/microfluidic/configuration_dl/md_domain.py
cases/microfluidic/configuration_dl/md_estimator.py
cases/microfluidic/configuration_dl/md_optimizer.py
cases/microfluidic/configuration_dl/md_sampler.py
cases/microfluidic/microfluid_file/__init__.py
cases/microfluidic/microfluid_file/rbc-trap-setup.mph
cases/sensitivity_analysis/__init__.py
cases/sensitivity_analysis/creator_structures.py
cases/sensitivity_analysis/sample.py
cases/sensitivity_analysis/configuration_sa/__init__.py
cases/sensitivity_analysis/configuration_sa/sa_domain.py
cases/sensitivity_analysis/configuration_sa/sa_estimator.py
cases/sensitivity_analysis/configuration_sa/sa_optimizer.py
cases/sensitivity_analysis/configuration_sa/sa_sampler.py
cases/sensitivity_analysis/configuration_sa/sa_surrogate_estimator.py
cases/sound_waves/__init__.py
cases/sound_waves/microphone_points.py
cases/sound_waves/sound_viz.py
cases/sound_waves/vizualization.py
gefest-0.1.0.dist-info/LICENSE.md
gefest-0.1.0.dist-info/METADATA
gefest-0.1.0.dist-info/WHEEL
gefest-0.1.0.dist-info/top_level.txt
gefest-0.1.0.dist-info/RECORD
