Metadata-Version: 2.1
Name: gefest
Version: 0.1.0
Summary: The toolbox for the generative design of physical objects
Home-page: https://github.com/ITMO-NSS-team/GEFEST
Author: NSS Lab
Author-email: itmo.nss.team@gmail.com
License: BSD 3-Clause
Classifier: License :: OSI Approved :: MIT License
Classifier: Programming Language :: Python :: 3.9
Classifier: Programming Language :: Python :: 3.10
Requires-Python: >=3.9
License-File: LICENSE.md
Requires-Dist: cython ==0.29.36
Requires-Dist: numba ==0.58.1
Requires-Dist: pandas ==1.4.4
Requires-Dist: numpy ==1.25.2
Requires-Dist: typing ==3.7.4.1
Requires-Dist: matplotlib ==3.6.3
Requires-Dist: seaborn ==0.9.0
Requires-Dist: MPh ==0.7.6
Requires-Dist: pickledb ==0.9.2
Requires-Dist: shapely ==2.0.1
Requires-Dist: pytest ==7.4.2
Requires-Dist: autodocsumm ==0.2.11
Requires-Dist: tqdm ==4.65.2
Requires-Dist: thegolem ==0.4.0
Requires-Dist: scipy ==1.9.3
Requires-Dist: scikit-image ==0.19.3
Requires-Dist: scikit-learn ==1.3.0
Requires-Dist: pydantic ==2.4.2
Requires-Dist: autodoc-pydantic ==2.0.1
Requires-Dist: pydantic-yaml ==1.1.1
Requires-Dist: PyYAML ==6.0.1
Requires-Dist: moviepy ==1.0.3
Requires-Dist: joblib ==1.3.2
Requires-Dist: loguru ==0.7.2
Requires-Dist: polygenerator ==0.2.0
Requires-Dist: flake8 ==6.0.0
Requires-Dist: brunette ==0.2.8
Requires-Dist: isort ==5.12.0
Requires-Dist: add-trailing-comma ==3.0.1
Requires-Dist: pep8-naming ==0.13.3
Requires-Dist: flake8-isort ==6.0.0
Requires-Dist: flake8-bugbear ==23.3.23
Requires-Dist: flake8-builtins ==2.1.0
Requires-Dist: flake8-commas ==2.1.0
Requires-Dist: flake8-variables-names ==0.0.5
Requires-Dist: flake8-docstrings ==1.7.0
Requires-Dist: flake8-fixme ==1.1.1
Requires-Dist: flake8-comments ==0.1.2
Requires-Dist: flake8-comprehensions ==3.14.0
Requires-Dist: flake8-clean-block ==0.1.2
